<Document>
  # Бармен

  Робота бармена досить проста: подавати напої. Люди підходять до вас і просять напої, а ваше завдання – просто вручити їх їм.

  <Box>
    Інгредієнти для цих напоїв можна знайти в різних місцях:
  </Box>
  <Box>
    <GuideEntityEmbed Entity="BoozeDispenser"/>
    <GuideEntityEmbed Entity="soda_dispenser"/>
    <GuideEntityEmbed Entity="VendingMachineBooze"/>
  </Box>

  <Box>
    Не забудьте контейнери для подачі напоїв!
  </Box>
  <Box>
    <GuideEntityEmbed Entity="DrinkGlass" Caption="Склянка"/>
    <GuideEntityEmbed Entity="DrinkGlassCoupeShaped"/>
    <GuideEntityEmbed Entity="DrinkShaker"/>
    <GuideEntityEmbed Entity="DrinkJigger"/>
  </Box>

  ## Напої

  Знання того, як приготувати замовлений напій, важливе. Ось різні напої в грі та їхні рецепти:

  <GuideReagentGroupEmbed Group="Drinks"/>
</Document>
